kompiler/__init__.py
kompiler/__main__.py
kompiler/constants.py
kompiler-1.2.1.dist-info/LICENSE
kompiler-1.2.1.dist-info/METADATA
kompiler-1.2.1.dist-info/WHEEL
kompiler-1.2.1.dist-info/entry_points.txt
kompiler-1.2.1.dist-info/top_level.txt
kompiler-1.2.1.dist-info/RECORD
